glitters-0.2.1.dist-info/METADATA
glitters-0.2.1.dist-info/WHEEL
glitters-0.2.1.dist-info/license_files/LICENSE
glitters/__init__.py
glitters/__init__.pyi
glitters/py.typed
glitters/glitters.abi3.so
glitters-0.2.1.dist-info/RECORD
