Metadata-Version: 2.3
Name: glitters
Version: 0.2.1
License-File: LICENSE
License: Apache License 2.0
Requires-Python: >=3.8
